streamlit_parameters/__init__.py
streamlit_parameters/demos/__init__.py
streamlit_parameters/demos/parameters.py
streamlit_parameters/hello.py
streamlit_parameters/parameters.py
streamlit_parameters-0.2.0.dist-info/LICENSE
streamlit_parameters-0.2.0.dist-info/METADATA
streamlit_parameters-0.2.0.dist-info/WHEEL
streamlit_parameters-0.2.0.dist-info/entry_points.txt
streamlit_parameters-0.2.0.dist-info/RECORD
