Metadata-Version: 2.1
Name: streamlit_parameters
Version: 0.2.0
Summary: Streamlit parameter management for page configuration
Home-page: https://github.com/splintered-reality/py_trees
License: BSD
Keywords: streamlit
Author: Daniel Stonier
Maintainer: Daniel Stonier
Maintainer-email: d.stonier@gmail.com
Requires-Python: >=3.8, !=2.7.*, !=3.0.*, !=3.1.*, !=3.2.*, !=3.3.*, !=3.4.*, !=3.5.*, !=3.6.*, !=3.7.*
Classifier: Environment :: Console
Classifier: Intended Audience :: Developers
Classifier: License :: OSI Approved :: BSD License
Classifier: License :: Other/Proprietary License
Classifier: Programming Language :: Python
Classifier: Programming Language :: Python :: 3
Classifier: Programming Language :: Python :: 3.8
Classifier: Programming Language :: Python :: 3.9
Classifier: Programming Language :: Python :: 3.10
Classifier: Programming Language :: Python :: 3.11
Classifier: Programming Language :: Python :: 3.12
Classifier: Programming Language :: Python :: 3.13
Classifier: Topic :: Scientific/Engineering :: Artificial Intelligence
Classifier: Topic :: Software Development :: Libraries
Requires-Dist: streamlit (>=1.30,<2)
Project-URL: Documentation, https://py-trees.readthedocs.io/en/devel/
Project-URL: Repository, https://github.com/splintered-reality/py_trees
